{
  "products": [
    {

      "name": "qdqw",
      "description": "wdqdq",
      "price": 23,
      "picture": "https://www.tabilga.kg/wp-content/uploads/2022/07/%D0%9A%D1%80%D0%BE%D0%B2%D0%B0%D1%82%D1%8C-%D0%B4%D0%B2%D1%83%D1%81%D0%BF%D0%B0%D0%BB%D1%8C%D0%BD%D0%B0%D1%8F-%D0%98%D0%BD%D0%B4%D0%B8%D1%80%D0%B0-1.jpg",
      "type": "wece",
      "id": 1
    },
    {
      "name": "кровать",
      "description": "some descr",
      "price": 1299,
      "picture": "https://www.tabilga.kg/wp-content/uploads/2022/07/%D0%9A%D1%80%D0%BE%D0%B2%D0%B0%D1%82%D1%8C-%D0%B4%D0%B2%D1%83%D1%81%D0%BF%D0%B0%D0%BB%D1%8C%D0%BD%D0%B0%D1%8F-%D0%98%D0%BD%D0%B4%D0%B8%D1%80%D0%B0-1.jpg",
      "type": "",
      "id": 2
    },
    {
      "name": "кровать",
      "description": "some descr",
      "price": 1299,
      "picture": "https://www.tabilga.kg/wp-content/uploads/2022/07/%D0%9A%D1%80%D0%BE%D0%B2%D0%B0%D1%82%D1%8C-%D0%B4%D0%B2%D1%83%D1%81%D0%BF%D0%B0%D0%BB%D1%8C%D0%BD%D0%B0%D1%8F-%D0%98%D0%BD%D0%B4%D0%B8%D1%80%D0%B0-1.jpg",
      "type": "",
      "id": 3
    },
    {
      "name": "кровать",
      "description": "some descr",
      "price": 1299,
      "picture": "https://www.tabilga.kg/wp-content/uploads/2022/07/%D0%9A%D1%80%D0%BE%D0%B2%D0%B0%D1%82%D1%8C-%D0%B4%D0%B2%D1%83%D1%81%D0%BF%D0%B0%D0%BB%D1%8C%D0%BD%D0%B0%D1%8F-%D0%98%D0%BD%D0%B4%D0%B8%D1%80%D0%B0-1.jpg",
      "type": "",
      "id": 4
    }, {
      "name": "кровать",
      "description": "some descr",
      "price": 1299,
      "picture": "https://www.tabilga.kg/wp-content/uploads/2022/07/%D0%9A%D1%80%D0%BE%D0%B2%D0%B0%D1%82%D1%8C-%D0%B4%D0%B2%D1%83%D1%81%D0%BF%D0%B0%D0%BB%D1%8C%D0%BD%D0%B0%D1%8F-%D0%98%D0%BD%D0%B4%D0%B8%D1%80%D0%B0-1.jpg",
      "type": "",
      "id": 5
    }, {
      "name": "кровать",
      "description": "some descr",
      "price": 1299,
      "picture": "https://www.tabilga.kg/wp-content/uploads/2022/07/%D0%9A%D1%80%D0%BE%D0%B2%D0%B0%D1%82%D1%8C-%D0%B4%D0%B2%D1%83%D1%81%D0%BF%D0%B0%D0%BB%D1%8C%D0%BD%D0%B0%D1%8F-%D0%98%D0%BD%D0%B4%D0%B8%D1%80%D0%B0-1.jpg",
      "type": "",
      "id": 6
    },
    {
      "name": "кровать",
      "description": "some descr",
      "price": 1299,
      "picture": "https://www.tabilga.kg/wp-content/uploads/2022/07/%D0%9A%D1%80%D0%BE%D0%B2%D0%B0%D1%82%D1%8C-%D0%B4%D0%B2%D1%83%D1%81%D0%BF%D0%B0%D0%BB%D1%8C%D0%BD%D0%B0%D1%8F-%D0%98%D0%BD%D0%B4%D0%B8%D1%80%D0%B0-1.jpg",
      "type": "",
      "id": 7
      "name": "AAAAaAA",
      "description": "some desctiption",
      "price": 8888,
      "picture": "sadsad",
      "type": "Phone",
      "id": 8
    },
    {
      "name": "AAAAaAA",
      "description": "some desctiption",
      "price": 8888,
      "picture": "sadsad",
      "type": "Phone",
      "id": 9
    },
    {
      "name": "AAAAaAA",
      "description": "some desctiption",
      "price": 8888,
      "picture": "sadsad",
      "type": "Phone",
      "id": 10
    },
  
    }
  ]
}